pyphen/__init__.py
pyphen/dictionaries/README_hyph_NO.txt
pyphen/dictionaries/README_hyph_be_BY.txt
pyphen/dictionaries/README_hyph_bg_BG.txt
pyphen/dictionaries/README_hyph_ca.txt
pyphen/dictionaries/README_hyph_cs_CZ.txt
pyphen/dictionaries/README_hyph_da_DK.txt
pyphen/dictionaries/README_hyph_de.txt
pyphen/dictionaries/README_hyph_el_GR.txt
pyphen/dictionaries/README_hyph_en_GB.txt
pyphen/dictionaries/README_hyph_en_US.txt
pyphen/dictionaries/README_hyph_es.txt
pyphen/dictionaries/README_hyph_et_EE.txt
pyphen/dictionaries/README_hyph_eu.txt
pyphen/dictionaries/README_hyph_fr.txt
pyphen/dictionaries/README_hyph_gl.txt
pyphen/dictionaries/README_hyph_hr_HR.txt
pyphen/dictionaries/README_hyph_hu_HU.txt
pyphen/dictionaries/README_hyph_is.txt
pyphen/dictionaries/README_hyph_it_IT.txt
pyphen/dictionaries/README_hyph_lt_LT.txt
pyphen/dictionaries/README_hyph_lv_LV.txt
pyphen/dictionaries/README_hyph_pl_PL.txt
pyphen/dictionaries/README_hyph_pt_BR.txt
pyphen/dictionaries/README_hyph_pt_PT.txt
pyphen/dictionaries/README_hyph_ro_RO.txt
pyphen/dictionaries/README_hyph_sk_SK.txt
pyphen/dictionaries/README_hyph_sl_SI.txt
pyphen/dictionaries/README_hyph_sq_AL.txt
pyphen/dictionaries/README_hyph_sr.txt
pyphen/dictionaries/README_hyph_sv.txt
pyphen/dictionaries/README_hyph_te_IN.txt
pyphen/dictionaries/README_hyph_th_TH.txt
pyphen/dictionaries/README_hyph_uk_UA.txt
pyphen/dictionaries/hyph_af_ZA.dic
pyphen/dictionaries/hyph_as_IN.dic
pyphen/dictionaries/hyph_be_BY.dic
pyphen/dictionaries/hyph_bg_BG.dic
pyphen/dictionaries/hyph_ca.dic
pyphen/dictionaries/hyph_cs_CZ.dic
pyphen/dictionaries/hyph_da_DK.dic
pyphen/dictionaries/hyph_de_AT.dic
pyphen/dictionaries/hyph_de_CH.dic
pyphen/dictionaries/hyph_de_DE.dic
pyphen/dictionaries/hyph_el_GR.dic
pyphen/dictionaries/hyph_en_GB.dic
pyphen/dictionaries/hyph_en_US.dic
pyphen/dictionaries/hyph_eo.dic
pyphen/dictionaries/hyph_es.dic
pyphen/dictionaries/hyph_et_EE.dic
pyphen/dictionaries/hyph_eu.dic
pyphen/dictionaries/hyph_fr.dic
pyphen-0.17.1.dist-info/COPYING.GPL
pyphen-0.17.1.dist-info/COPYING.LGPL
pyphen-0.17.1.dist-info/COPYING.MPL
pyphen-0.17.1.dist-info/LICENSE
pyphen-0.17.1.dist-info/WHEEL
pyphen-0.17.1.dist-info/METADATA
pyphen-0.17.1.dist-info/RECORD
